MANIFEST.in
setup.py
ext/_parser.c
ext/http_parser.c
ext/http_parser.h
src/geventhttpclient/__init__.py
src/geventhttpclient/cacert.pem
src/geventhttpclient/client.py
src/geventhttpclient/connectionpool.py
src/geventhttpclient/httplib.py
src/geventhttpclient/response.py
src/geventhttpclient/url.py
src/geventhttpclient_c.egg-info/PKG-INFO
src/geventhttpclient_c.egg-info/SOURCES.txt
src/geventhttpclient_c.egg-info/dependency_links.txt
src/geventhttpclient_c.egg-info/requires.txt
src/geventhttpclient_c.egg-info/top_level.txt