Metadata-Version: 1.0
Name: geventhttpclient-c
Version: 1.0a-t3
Summary: http client library for gevent
Home-page: UNKNOWN
Author: Antonin Amand
Author-email: antonin.amand@gmail.com
License: UNKNOWN
Platform: UNKNOWN
